{
    "index": "K1F-hG165g4",
    "title": "Pesticidewise: minor pesticide spill",
    "url": "https://www.youtube.com/watch?v=K1F-hG165g4",
    "category": "Education",
    "tasks": [
        {
            "task": "Spill Containment and Cleanup",
            "subtasks": [
                "Identify and assess the spill",
                "Retrieve spill kit containing sand or sawdust",
                "Apply sand or sawdust to contain and absorb the liquid",
                "Monitor spill progression and act promptly",
                "Gather contaminated material into a plastic bag",
                "Seal and label the plastic bag for safe disposal",
                "Access additional information on pesticides and personal protective equipment (PPE) via www.cdc.gov.au"
            ]
        },
        {
            "task": "MAINTASK: Spill Containment and Cleanup",
            "subtasks": [
                "Identify and assess the spill",
                "Retrieve spill kit containing sand or sawdust",
                "Apply sand or sawdust to contain and absorb the liquid",
                "Monitor spill progression and act promptly",
                "Gather contaminated material into a plastic bag",
                "Seal and label the plastic bag for safe disposal",
                "Access additional information on pesticides and personal protective equipment (PPE) via www.cdc.gov.au"
            ]
        }
    ]
}