{
    "index": "LIsPequ2nXo",
    "title": "Promoting Climate Smart Agricultural Initiatives in Cambodia",
    "url": "https://www.youtube.com/watch?v=LIsPequ2nXo",
    "category": "Nonprofits & Activism",
    "tasks": [
        {
            "task": "Farmers responding to climate change in Cambodia through agricultural projects",
            "subtasks": [
                "Rehabilitating and climate-proofing irrigation systems",
                "Implementing laser land leveling to improve water conservation",
                "Testing weather-indexed crop insurance for rice farmers",
                "Developing a certification system for more resilient rice seeds",
                "Creating employment opportunities for women in rice farming"
            ]
        },
        {
            "task": "Government support for climate resilience in agriculture",
            "subtasks": [
                "Preparing strategic programs for climate resilience",
                "Implementing seven investment projects for comprehensive support",
                "Specific focus on the agricultural sector through two investment projects"
            ]
        },
        {
            "task": "Economic, social, and environmental sustainability in rice farming",
            "subtasks": [
                "Enhancing rice production in major provinces",
                "Improving irrigation water use efficiency",
                "Supporting farmers to manage climate risks",
                "Ensuring availability and quality of certified rice seeds",
                "Promoting gender equality through job creation for women"
            ]
        },
        {
            "task": "Farmers rehabilitating and adapting irrigation systems",
            "subtasks": [
                "Inspecting existing irrigation infrastructure for damage",
                "Repairing damaged canals, pipes, and pumps",
                "Installing climate-resilient components (e.g., flood-proofing)",
                "Testing rehabilitation projects' effectiveness"
            ]
        },
        {
            "task": "Farmers implementing laser land leveling",
            "subtasks": [
                "Adjusting field elevation using leveled laser systems",
                "Ensuring proper water distribution in fields",
                "Adjusting irrigation schedules based on improved water use"
            ]
        },
        {
            "task": "Farmers adopting weather-indexed crop insurance",
            "subtasks": [
                "Understanding index-based insurance terms",
                "Registering for the insurance scheme",
                "Collecting premiums",
                "Filing claims when eligible"
            ]
        },
        {
            "task": "Farmers using certified rice seeds",
            "subtasks": [
                "Obtaining certified seeds from distribution centers",
                "Storing seeds properly to maintain viability",
                "Planting the seeds at the right time and depth",
                "Monitoring seed performance and sharing feedback for future improvements"
            ]
        },
        {
            "task": "Women's participation in employment opportunities",
            "subtasks": [
                "Participating in vocational training programs",
                "Engaging in entrepreneurship activities related to agriculture",
                "Collaborating in community projects that benefit from climate-resilient practices"
            ]
        },
        {
            "task": "Implementing seed certification systems",
            "subtasks": [
                "Sampling rice seeds for testing",
                "Conducting performance trials under various conditions",
                "Issuing certifications based on tests results",
                "Providing tools and training to farmers on seed selection and protection"
            ]
        },
        {
            "task": "Assisting in water use improvement",
            "subtasks": [
                "Installing climate-proof irrigation systems",
                "Monitoring water usage and adjusting practices accordingly"
            ]
        },
        {
            "task": "Supporting infrastructure rehabilitation",
            "subtasks": [
                "Assessing existing infrastructure for climate resilience",
                "Planning and designing adaptive measures",
                "Supervising construction and maintenance of infrastructure"
            ]
        },
        {
            "task": "Increasing rice production",
            "subtasks": [
                "Expanding cropland",
                "Applying better farming practices",
                "Using precision agriculture tools (if applicable, but the transcript mentions laser land leveling, not drones or new tech)"
            ]
        },
        {
            "task": "Enhancing community support systems",
            "subtasks": [
                "Organizing farmer cooperatives for mutual assistance",
                "Conducting extension programs on climate-resilient techniques",
                "Providing psychological support for farmers facing climate stress"
            ]
        },
        {
            "task": "Protecting natural resources",
            "subtasks": [
                "Diversifying crops to reduce dependency",
                "Implementing agroforestry practices",
                "Restoring degraded soils"
            ]
        },
        {
            "task": "Participating in agroforestry efforts",
            "subtasks": [
                "Planting trees on farmland"
            ]
        },
        {
            "task": "Supporting women's economic empowerment in agriculture",
            "subtasks": [
                "Offering training on business development",
                "Facilitating access to credit and markets",
                "Encouraging women's participation in decision-making"
            ]
        },
        {
            "task": "Women taking on new agricultural roles",
            "subtasks": [
                "Engaging in field management",
                "Participating in irrigation system operations",
                "Managing seed certification centers"
            ]
        },
        {
            "task": "Rehabilitating irrigation systems",
            "subtasks": [
                "Repairing existing canals and pipelines",
                "Installing floodgates and other barriers for flood protection",
                "Upgrading pumping stations for better water flow"
            ]
        },
        {
            "task": "Enrolling in and utilizing weather-indexed crop insurance",
            "subtasks": [
                "Understanding the index-based trigger for compensation",
                "Reporting claims after adverse weather events",
                "Attending insurance training workshops"
            ]
        },
        {
            "task": "Participating in the improved seed distribution scheme",
            "subtasks": [
                "Accessing certified seeds from local suppliers",
                "Upgrading seed storage facilities to maintain quality"
            ]
        },
        {
            "task": "Practicing water conservation through laser land leveling",
            "subtasks": [
                "Adjusting water application depths based on land topography",
                "Monitoring soil moisture levels and adjusting irrigation frequency",
                "Participating in demonstrations or trials of laser land leveling techniques"
            ]
        },
        {
            "task": "Maintaining crop health through better seed selection and practices",
            "subtasks": [
                "Using resistant varieties to withstand local weather conditions",
                "Applying integrated pest management techniques"
            ]
        },
        {
            "task": "Using certified rice seeds",
            "subtasks": [
                "Storing seeds in dry, cool conditions",
                "Monitoring seed viability and reordering when needed"
            ]
        },
        {
            "task": "Adhering to climate-resilience practices",
            "subtasks": [
                "Following government-implemented guidelines for sustainable farming"
            ]
        },
        {
            "task": "Enrolling in the pilot weather-indexed crop insurance",
            "subtasks": [
                "Understanding the terms and benefits of the insurance",
                "Paying premiums and managing claims processes"
            ]
        },
        {
            "task": "Participating in climate-resilient agriculture initiatives",
            "subtasks": [
                "Adhering to project timelines and requirements",
                "Cooperating with project implementers for infrastructure repairs",
                "Obtaining and planting certified rice seeds"
            ]
        },
        {
            "task": "",
            "subtasks": []
        },
        {
            "task": "Using certified rice seeds to improve resilience",
            "subtasks": [
                "Acquiring certified seeds from local distributors",
                "Properly storing and protecting certi fats"
            ]
        },
        {
            "task": "Participating in the climate-resilience rice project",
            "subtasks": [
                "Using rehabilitated irrigation systems",
                "Planting certified rice seeds",
                "Enrolling in weather-indexed crop insurance"
            ]
        },
        {
            "task": "Using laser land levelling for water conservation",
            "subtasks": []
        },
        {
            "task": "Enrolling in weather-indexed crop insurance",
            "subtasks": []
        },
        {
            "task": "Planting certified rice seeds",
            "subtasks": []
        },
        {
            "task": "Participating in infrastructure rehabilitation",
            "subtasks": [
                "Engaging in agricultural training, participating in income-generating activities, and accessing employment opportunities created by the project."
            ]
        },
        {
            "task": "Farmers' tasks",
            "subtasks": [
                "Rehabilitate irrigation systems (A. InspectDamage, B. Repaircomponents, C. Testefficacy)",
                "Implement laser land leveling (A. AdjustTopography, B. MonitorWaterDistribution, C. AdaptIrrigationSchedules)",
                "Use certified rice seeds (A. Obtainseeds, B. Storeproperly, C. Plantatrighttimes)",
                "Participate in weather-indexed insurance (A.Understandpolicies, B.Rstyleclaims)"
            ]
        },
        {
            "task": "Project team tasks",
            "subtasks": [
                "Establish seed certification processes (A.Sampleseeds, B.Testperformance, C.Issuecertifications)",
                "Rehabilitateirrigation infrastructure (A.Identifyneeds, B.Desigerrals, C.Supervisconstruction)",
                "Educate farmers on water use efficiency techniques (A.Demonstrateleveling, B.Monitorresiliencepractices)"
            ]
        },
        {
            "task": "Gender-related tasks",
            "subtasks": [
                "Women engage in job training (A.Learnfarmingpractices, B.Accessmentoring)",
                "Createwomen-centricenterprises (A.Cultivateproducts, B.Marketlocalgoods)",
                "Support women's participation (A.Providetools, B.Organize networking events)"
            ]
        },
        {
            "task": "Farmers rehabilitating and adapting irrigation systems",
            "subtasks": [
                "Inspecting existing irrigation infrastructure for damage",
                "Repairing damaged canals, pipes, and pumps",
                "Testing rehabilitation projects' effectiveness"
            ]
        },
        {
            "task": "Farmers implementing laser land leveling",
            "subtasks": [
                "Adjusting field elevation using leveled laser systems",
                "Ensuring proper water distribution in fields",
                "Adjusting irrigation schedules based on improved water use"
            ]
        },
        {
            "task": "Farmers adopting weather-indexed crop insurance",
            "subtasks": [
                "Understanding index-based insurance terms",
                "Registering for the insurance scheme",
                "Collecting premiums",
                "Filing claims when eligible"
            ]
        },
        {
            "task": "Women's participation in employment opportunities",
            "subtasks": [
                "Participating in vocational training programs",
                "Engaging in entrepreneurship activities related to agriculture"
            ]
        },
        {
            "task": "Implementing seed certification systems",
            "subtasks": [
                "Sampling rice seeds for testing",
                "Conducting performance trials under various conditions",
                "Issuing certifications based on tests results"
            ]
        },
        {
            "task": "Assisting in water use improvement",
            "subtasks": [
                "Installing climate-proof irrigation systems",
                "Monitoring water usage and adjusting practices accordingly"
            ]
        },
        {
            "task": "Supporting infrastructure rehabilitation",
            "subtasks": [
                "Assessing existing infrastructure for climate resilience",
                "Planning and designing adaptive measures",
                "Supervising construction and maintenance of infrastructure"
            ]
        },
        {
            "task": "Farmers Rehabilitating and Adapting Irrigation Systems**",
            "subtasks": []
        },
        {
            "task": "Farmers Implementing Laser Land Leveling**",
            "subtasks": []
        },
        {
            "task": "Farmers Adopting Weather-Indexed Crop Insurance**",
            "subtasks": []
        },
        {
            "task": "Women's Participation in Employment Opportunities**",
            "subtasks": []
        },
        {
            "task": "Implementing Seed Certification Systems**",
            "subtasks": []
        },
        {
            "task": "Assisting in Water Use Improvement**",
            "subtasks": []
        },
        {
            "task": "Supporting Infrastructure Rehabilitation**",
            "subtasks": []
        },
        {
            "task": "Farmers rehabilitating and adapting irrigation systems",
            "subtasks": [
                "Inspecting existing irrigation infrastructure for damage",
                "Repairing damaged canals, pipes, and pumps",
                "Testing rehabilitation projects' effectiveness"
            ]
        },
        {
            "task": "Farmers implementing laser land leveling",
            "subtasks": [
                "Adjusting field elevation using leveled laser systems",
                "Ensuring proper water distribution in fields",
                "Adjusting irrigation schedules based on improved water use"
            ]
        },
        {
            "task": "Farmers adopting weather-indexed crop insurance",
            "subtasks": [
                "Understanding index-based insurance terms",
                "Registering for the insurance scheme",
                "Collecting premiums",
                "Filing claims when eligible"
            ]
        },
        {
            "task": "Women's participation in employment opportunities",
            "subtasks": [
                "Participating in vocational training programs",
                "Engaging in entrepreneurship activities related to agriculture"
            ]
        },
        {
            "task": "Implementing seed certification systems",
            "subtasks": [
                "Sampling rice seeds for testing",
                "Conducting performance trials under various conditions",
                "Issuing certifications based on tests results"
            ]
        },
        {
            "task": "Assisting in water use improvement",
            "subtasks": [
                "Installing climate-proof irrigation systems",
                "Monitoring water usage and adjusting practices accordingly"
            ]
        },
        {
            "task": "Supporting infrastructure rehabilitation",
            "subtasks": [
                "Assessing existing infrastructure for climate resilience",
                "Planning and designing adaptive measures",
                "Supervising construction and maintenance of infrastructure"
            ]
        }
    ]
}