{
    "index": "u7E1Lgmbioc",
    "title": "Unknown Title",
    "url": "https://www.youtube.com/watch?v=u7E1Lgmbioc",
    "category": "Unknown Category",
    "tasks": [
        {
            "task": "Grow peanuts from grocery store nuts",
            "subtasks": [
                "Prepare raw peanuts",
                "Plant peanuts",
                "Provide optimal growing conditions",
                "Watering",
                "Monitor plant growth",
                "Harvest peanuts"
            ]
        },
        {
            "task": "Save peanuts for planting",
            "subtasks": []
        },
        {
            "task": "Grow peanuts from grocery store nuts",
            "subtasks": [
                "Prepare raw peanuts",
                "Plant peanuts",
                "Provide optimal growing conditions",
                "Water peppers when soil feels dry 1 inch down",
                "Monitor plant growth",
                "Harvest peppers",
                "Save peppers for planting"
            ]
        },
        {
            "task": "Grow peanuts from grocery store nuts**",
            "subtasks": [
                "Prepare raw peanuts**",
                "Plant peanuts**",
                "Provide optimal growing conditions**",
                "Water peanuts when soil feels dry 1 inch down**",
                "Monitor plant growth**",
                "Harvest peanuts**",
                "Save peanuts for planting**"
            ]
        },
        {
            "task": "Grow peanuts from grocery store nuts",
            "subtasks": [
                "Prepare raw peanuts",
                "Plant peanuts",
                "Provide optimal growing conditions",
                "Water peanuts when soil feels dry 1 inch down",
                "Monitor plant growth",
                "Harvest peanuts",
                "Save peanuts for planting"
            ]
        }
    ]
}