{
    "index": "vRGQuoCuC8o",
    "title": "Not Your Basic Yard Mower #agriculture #tractor #farm #NewHolland #CaseIH #JohnDeere #mower #harvest",
    "url": "https://www.youtube.com/watch?v=vRGQuoCuC8o",
    "category": "Entertainment",
    "tasks": [
        {
            "task": "Planting potatoes in a field.",
            "subtasks": [
                "Walking through the field.",
                "Bending down to reach the soil.",
                "Digging a shallow hole using a gardening tool.",
                "Carefully placing a potato piece into the hole.",
                "Covering the potato with soil, using hands or a tool."
            ]
        },
        {
            "task": "Checking for signs of weeds.",
            "subtasks": [
                "Walking through the planted area.",
                "Bent-knee inspection of the ground level.",
                "Identifying weeds versus crop plants.",
                "Carefully pulling out weed roots."
            ]
        },
        {
            "task": "Watering the potato plants.",
            "subtasks": [
                "Retrieving a watering can or hose.",
                "Walking through rows of plants, holding the watering tool.",
                "Directing water towards the base of each plant.",
                "Ensuring even coverage across all the plants."
            ]
        },
        {
            "task": "Spraying pesticide.",
            "subtasks": [
                "Putting on protective gear.",
                "Mixing pesticide according to instructions.",
                "Using a sprayer to apply pesticide to the plants.",
                "Ensuring complete coverage without overspray."
            ]
        },
        {
            "task": "Harv ...",
            "subtasks": []
        }
    ]
}